prepextend/__init__.py
prepextend/_config/__init__.py
prepextend/_config/config.py
prepextend/common/__init__.py
prepextend/common/api.py
prepextend/io/__init__.py
prepextend/io/api.py
prepextend/io/prep_read_main.py
prepextend/management/__init__.py
prepextend/management/api.py
prepextend/management/flow_manage_main.py
prepextend/run/__init__.py
prepextend/run/api.py
prepextend/run/run_prep.py
prepextend-2020.2.1.2.dist-info/LICENSE
prepextend-2020.2.1.2.dist-info/METADATA
prepextend-2020.2.1.2.dist-info/WHEEL
prepextend-2020.2.1.2.dist-info/top_level.txt
prepextend-2020.2.1.2.dist-info/RECORD
